kibana_dashboard_api/__init__.py
kibana_dashboard_api/common.py
kibana_dashboard_api/dashboards.py
kibana_dashboard_api/paneltools.py
kibana_dashboard_api/visualizations.py
kibana_dashboard_api-0.1.2.dist-info/DESCRIPTION.rst
kibana_dashboard_api-0.1.2.dist-info/METADATA
kibana_dashboard_api-0.1.2.dist-info/metadata.json
kibana_dashboard_api-0.1.2.dist-info/RECORD
kibana_dashboard_api-0.1.2.dist-info/top_level.txt
kibana_dashboard_api-0.1.2.dist-info/WHEEL
