Metadata-Version: 2.0
Name: kibana-dashboard-api
Version: 0.1.2
Summary: Manages Kiabana visualizations and dashboards.
Home-page: https://github.com/harabchuk/kibana-dashboard-api
Author: Aliaksei Harabchuk
Author-email: aliaksei.harabchuk@gmail.com
License: MIT
Keywords: kibana elasticsearch
Platform: UNKNOWN
Classifier: Development Status :: 3 - Alpha
Classifier: License :: OSI Approved :: MIT License
Classifier: Programming Language :: Python :: 3
Classifier: Programming Language :: Python :: 3.6
Classifier: Topic :: Software Development :: Libraries
Requires-Dist: elasticsearch
